{"tagline":"Displays the /humans.txt file of a website in a nicely designed Application.","note":"Don't delete this file! It's used internally to help with page regeneration.","body":"humanstxt.app\r\n=============\r\n\r\nDescription\r\n-----------\r\nAn App to retrieve and Parse the humans.txt File of a website. Will be released on the AppStore soon ;)\r\nVisit http://humanstxt.org for more information on humans.txt.\r\nPlease note that this App won't work for every humans.txt file.\r\nIt was programmed to parse the Syntax declared at http://humanstxt.org/Standard.html.\r\nSites like Google (http://www.google.com/humans.txt) don't use the standard syntax, so this App won't display the Information correctly.\r\n\r\nLicense\r\n-------\r\nIn addition to the BSD-2 license below, I ask that you do not publicly distribute the app as a whole in binary form (e.g. on the App Store).\r\n\r\n    Copyright (c) 2012, Lars Schwegmann\r\n    All rights reserved.\r\n\r\n    Redistribution and use in source and binary forms, with or without\r\n    modification, are permitted provided that the following conditions are met:\r\n\r\n    * Redistributions of source code must retain the above copyright notice, this\r\n      list of conditions and the following disclaimer.\r\n\r\n    * Redistributions in binary form must reproduce the above copyright notice,\r\n      this list of conditions and the following disclaimer in the documentation\r\n      and/or other materials provided with the distribution.\r\n\r\n    THIS SOFTWARE IS PROVIDED BY THE COPYRIGHT HOLDERS AND CONTRIBUTORS \"AS IS\" AND\r\n    ANY EXPRESS OR IMPLIED WARRANTIES, INCLUDING, BUT NOT LIMITED TO, THE IMPLIED\r\n    WARRANTIES OF MERCHANTABILITY AND FITNESS FOR A PARTICULAR PURPOSE ARE\r\n    DISCLAIMED. IN NO EVENT SHALL THE COPYRIGHT HOLDER OR CONTRIBUTORS BE LIABLE\r\n    FOR ANY DIRECT, INDIRECT, INCIDENTAL, SPECIAL, EXEMPLARY, OR CONSEQUENTIAL\r\n    DAMAGES (INCLUDING, BUT NOT LIMITED TO, PROCUREMENT OF SUBSTITUTE GOODS\r\n    OR SERVICES; LOSS OF USE, DATA, OR PROFITS; OR BUSINESS INTERRUPTION) HOWEVER\r\n    CAUSED AND ON ANY THEORY OF LIABILITY, WHETHER IN CONTRACT, STRICT LIABILITY,\r\n    OR TORT (INCLUDING NEGLIGENCE OR OTHERWISE) ARISING IN ANY WAY OUT OF THE USE\r\n    OF THIS SOFTWARE, EVEN IF ADVISED OF THE POSSIBILITY OF SUCH DAMAGE.\r\n\r\nSupport\r\n-------\r\nIf you need help or find a bug contact me via:\r\n\r\n * Twitter: @larsschwegmann\r\n * Email: larsob@me.com\r\n\r\nIf you want to support this project, please help me with further development.\r\nIf you are no developer, you can also buy me a coke by donating to my paypal account by clicking on this link: https://www.paypal.com/cgi-bin/webscr?cmd=_s-xclick&hosted_button_id=6CP86VYT57UU4","name":"humanstxt.app","google":"UA-32097759-1"}